psr_graf-2.1.3-py3.13-nspkg.pth
psr/graf/__init__.py
psr/graf/graf.py
psr_graf-2.1.3.dist-info/METADATA
psr_graf-2.1.3.dist-info/WHEEL
psr_graf-2.1.3.dist-info/namespace_packages.txt
psr_graf-2.1.3.dist-info/top_level.txt
psr_graf-2.1.3.dist-info/RECORD
