Metadata-Version: 2.1
Name: psr-graf
Version: 2.1.3
Summary: Utility module to read PSR Sddp's hdr/bin result file pairs.
Home-page: https://github.com/psrenergy/pygraf
Author: PSR
Author-email: d.parrini@gmail.com
Classifier: Programming Language :: Python :: 3
Classifier: License :: OSI Approved :: MIT License
Classifier: Operating System :: OS Independent
Requires-Python: >=3.9
